LICENSE
MANIFEST.in
README
README.rst
requirements.txt
setup.py
./nlring/__init__.py
./nlring/ring.py
./nlring/ssh.py
nlring.egg-info/PKG-INFO
nlring.egg-info/SOURCES.txt
nlring.egg-info/dependency_links.txt
nlring.egg-info/requires.txt
nlring.egg-info/top_level.txt