Metadata-Version: 1.1
Name: nlring
Version: 1.0.1
Summary: NLNOG Ring task execution library
Home-page: https://github.com/AlexForster/nlring
Author: Alex Forster
Author-email: alex@alexforster.com
License: 3-Clause ("New") BSD license
Download-URL: https://pypi.python.org/pypi/nlring
Platform: UNKNOWN
Classifier: Development Status :: 5 - Production/Stable
Classifier: Intended Audience :: Developers
Classifier: License :: OSI Approved :: BSD License
Classifier: Operating System :: MacOS :: MacOS X
Classifier: Operating System :: POSIX
Classifier: Operating System :: POSIX :: BSD
Classifier: Operating System :: POSIX :: Linux
Classifier: Programming Language :: Python
Classifier: Programming Language :: Python :: 2
Classifier: Programming Language :: Python :: 2.7
Classifier: Topic :: Software Development :: Libraries
